num2heb/__init__.py
num2heb-0.1.14.dist-info/METADATA
num2heb-0.1.14.dist-info/WHEEL
num2heb-0.1.14.dist-info/top_level.txt
num2heb-0.1.14.dist-info/RECORD
