Metadata-Version: 2.1
Name: num2heb
Version: 0.1.14
Summary: A Function to convert a number into words in Hebrew
Home-page: https://github.com/azoulaynoam/num2heb
Author: Noam Azoulay
Author-email: noam@na-systems.com
Classifier: Programming Language :: Python :: 3
Classifier: License :: OSI Approved :: MIT License
Classifier: Operating System :: OS Independent
Requires-Python: >=3.6
